{
  "userInfo": [
    {
      "id": "0",
      "userId": "test01",
      "userPassword": "1234",
      "userName": "홍길동",
      "userImage": "/images/profile01.jpg",
      "userPhone": "010-0000-0000",
      "userCompany": "NPLUS(네파)",
      "userTeam": "",
      "jobTitle": "과장"
    },
    {
      "id": "1",
      "userId": "test02",
      "userPassword": "5678",
      "userName": "강아지",
      "userImage": "/images/profile02.jpg",
      "userPhone": "010-0000-0000",
      "userCompany": "STYLESHIP",
      "userTeam": "CR",
      "jobTitle": "사원"
    },
    {
      "id": "2",
      "userId": "test03",
      "userPassword": "0000",
      "userName": "임꺽정",
      "userImage": "/images/profile03.jpg",
      "userPhone": "010-0000-0000",
      "userCompany": "미스토코리아(주)",
      "userTeam": "FILA",
      "jobTitle": "대리"
    },
    {
      "id": "3",
      "userId": "test04",
      "userPassword": "1111",
      "userName": "배고파",
      "userImage": "/images/profile03.jpg",
      "userPhone": "010-0000-0000",
      "userCompany": "NPLUS(네파)",
      "userTeam": "",
      "jobTitle": "사원"
    },
    {
      "id": "4",
      "userId": "test05",
      "userPassword": "0000",
      "userName": "김케즈",
      "userImage": "/images/profile01.jpg",
      "userPhone": "010-0000-0000",
      "userCompany": "미스토코리아(주)",
      "userTeam": "KEDS",
      "jobTitle": "사원"
    },
    {
      "id": "5",
      "userId": "test06",
      "userPassword": "0000",
      "userName": "고구마",
      "userImage": "/images/profile02.jpg",
      "userPhone": "010-0000-0000",
      "userCompany": "STYLESHIP",
      "userTeam": "UXI",
      "jobTitle": "대리"
    },
    {
      "id": "6",
      "userId": "test07",
      "userPassword": "0000",
      "userName": "바나나",
      "userImage": "/images/profile01.jpg",
      "userPhone": "010-0000-0000",
      "userCompany": "STYLESHIP",
      "userTeam": "DV",
      "jobTitle": "과장"
    }
  ],
  "projectList": [
    {
      "id": "0",
      "writer": "홍길동",
      "projectNo": 84739,
      "projectDate": "2025-08-06",
      "projectCompany": "NPLUS(네파)",
      "projectBrand": "NEPA",
      "projectSort": "외부몰",
      "projectTitle": "○ [키즈] WINTER VACANCE 다운 프리오더 (8/13~9/21)",
      "projectStatus": "completion",
      "projectDeadline": "2025-10-20",
      "projectContent": "안녕하세요, 라이카 카메라 코리아 기획전 제작 요청드립니다.",
      "projectTeam": "SR"
    },
    {
      "id": "1",
      "writer": "홍길동",
      "projectNo": 84740,
      "projectDate": "2025-09-06",
      "projectCompany": "미스토코리아(주)",
      "projectBrand": "FILA",
      "projectSort": "이벤트",
      "projectTitle": "9월 로그데이터",
      "projectStatus": "receipt",
      "projectDeadline": "2025-10-20",
      "projectContent": "안녕하세요, 라이카 카메라 코리아 기획전 제작 요청드립니다.",
      "projectTeam": "UXI"
    },
    {
      "id": "2",
      "writer": "임꺽정",
      "projectNo": 84741,
      "projectDate": "2025-10-06",
      "projectCompany": "미스토코리아(주)",
      "projectBrand": "FILA",
      "projectSort": "프로모션",
      "projectTitle": "무아몽 25FW 등록",
      "projectStatus": "cancel",
      "projectDeadline": "2025-10-20",
      "projectContent": "안녕하세요, 라이카 카메라 코리아 기획전 제작 요청드립니다.",
      "projectTeam": "CR"
    },
    {
      "id": "3",
      "writer": "강아지",
      "projectNo": 84742,
      "projectDate": "2025-10-15",
      "projectCompany": "NPLUS(네파)",
      "projectBrand": "NEPA",
      "projectSort": "기획전",
      "projectTitle": "[클럽] 배틀레디2 다크니스 프로모션 파일 송부 요청",
      "projectStatus": "progress",
      "projectDeadline": "2025-10-20",
      "projectContent": "안녕하세요, 라이카 카메라 코리아 기획전 제작 요청드립니다.",
      "projectTeam": "DEV"
    },
    {
      "id": "4",
      "writer": "강아지",
      "projectNo": 84743,
      "projectDate": "2025-10-17",
      "projectCompany": "NPLUS(네파)",
      "projectBrand": "NEPA",
      "projectSort": "기획전",
      "projectTitle": "[클럽] 배틀레디2 다크니스 프로모션 파일 송부 요청",
      "projectStatus": "hold",
      "projectDeadline": "2025-10-20",
      "projectContent": "안녕하세요, 라이카 카메라 코리아 기획전 제작 요청드립니다.",
      "projectTeam": "CR"
    },
    {
      "id": "1760926380316",
      "projectNo": 84744,
      "projectDate": "2025-10-20",
      "projectStatus": "receipt",
      "projectTeam": "CR",
      "writer": "강아지",
      "projectCompany": "STYLESHIP",
      "projectBrand": "FILA",
      "projectSort": "프로모션",
      "projectTitle": "프로젝트 생성 테스트",
      "projectContent": "프로모션 생성 테스트입니다.",
      "projectDeadline": "2025-10-30"
    },
    {
      "id": "1760942585880",
      "projectNo": 84745,
      "projectDate": "2025-10-20",
      "projectStatus": "receipt",
      "projectTeam": "CR",
      "writer": "홍길동",
      "projectCompany": "NPLUS(네파)",
      "projectBrand": "NEPA",
      "projectSort": "이벤트",
      "projectTitle": "dd",
      "projectContent": "test!",
      "projectDeadline": "2025-10-24"
    },
    {
      "id": "1761643358998",
      "projectNo": 84746,
      "projectDate": "2025-10-28",
      "projectStatus": "receipt",
      "projectTeam": "CR",
      "writer": "홍길동",
      "projectCompany": "NPLUS(네파)",
      "projectBrand": "NEPA",
      "projectSort": "기획전",
      "projectTitle": "ㅇㅇ",
      "projectContent": "신규 프로젝트 확인입니다. ",
      "projectDeadline": ""
    },
    {
      "id": "1761643730384",
      "projectNo": 84747,
      "projectDate": "2025-10-28",
      "projectStatus": "receipt",
      "projectTeam": "CR",
      "writer": "홍길동",
      "projectCompany": "NPLUS(네파)",
      "projectBrand": "NEPA",
      "projectSort": "이벤트",
      "projectTitle": "dfsdf",
      "projectContent": "todtjd\n테스트\n줄바꿈\n확인용\n확인 ㄱㄱㄱ",
      "projectDeadline": ""
    },
    {
      "id": "1761643807048",
      "projectNo": 84748,
      "projectDate": "2025-10-28T02:44:53.917Z",
      "projectStatus": "receipt",
      "projectTeam": "CR",
      "writer": "홍길동",
      "projectCompany": "NPLUS(네파)",
      "projectBrand": "NEPA",
      "projectSort": "이벤트",
      "projectTitle": "sg",
      "projectContent": "ej~~~~ 넎어볼게요\n엔터\n엔터\n엔터\n엔터\n엔터\n엔터\n엔터\n스크로ㅓㄹ확인!",
      "projectDeadline": ""
    },
    {
      "id": "1761705893917",
      "projectNo": 84749,
      "projectDate": "2025-10-29T02:44:53.917Z",
      "projectStatus": "receipt",
      "projectTeam": "CR",
      "writer": "홍길동",
      "projectCompany": "NPLUS(네파)",
      "projectBrand": "NEPA",
      "projectSort": "기획전",
      "projectTitle": "ㅇㅇㅇ",
      "projectContent": "ㅇ",
      "projectDeadline": ""
    },
    {
      "id": "1761724296366",
      "projectNo": 84750,
      "projectDate": "2025-10-29T07:51:36.366Z",
      "projectStatus": "receipt",
      "projectTeam": "CR",
      "writer": "홍길동",
      "projectCompany": "NPLUS(네파)",
      "projectBrand": "NEPA",
      "projectSort": "기능 수정/추가",
      "projectTitle": "nEW 테슽 ... ㅡㅌ... ",
      "projectContent": "TEST\nTESTTEST\nTEST\nTEST\nTEST\nTEST\nTEST\nTEST\nTEST",
      "projectDeadline": ""
    }
  ],
  "comments": [
    {
      "id": "9495",
      "projectId": 84745,
      "userId": "0",
      "type": "_us",
      "name": "홍길동",
      "profile": "/images/profile01.jpg",
      "time": "오후 5:51",
      "createdAt": "2025-10-27T08:51:36.826Z",
      "text": "test!"
    },
    {
      "id": "268d",
      "projectId": 84745,
      "userId": "0",
      "type": "_us",
      "name": "홍길동",
      "profile": "/images/profile01.jpg",
      "time": "오후 5:51",
      "createdAt": "2025-10-27T08:51:42.081Z",
      "text": "홍길동이 썼어요"
    },
    {
      "id": "a5eb",
      "projectId": 84745,
      "userId": "1",
      "type": "_us",
      "name": "강아지",
      "profile": "/images/profile02.jpg",
      "time": "오후 5:52",
      "createdAt": "2025-10-27T08:52:00.249Z",
      "text": "test!"
    },
    {
      "id": "bc2b",
      "projectId": 84745,
      "userId": "1",
      "type": "_us",
      "name": "강아지",
      "profile": "/images/profile02.jpg",
      "time": "오후 5:52",
      "createdAt": "2025-10-27T08:52:05.177Z",
      "text": "강아지가 썼어요"
    },
    {
      "id": "a987",
      "projectId": 84745,
      "userId": "2",
      "type": "_us",
      "name": "임꺽정",
      "profile": "/images/profile03.jpg",
      "time": "오후 5:52",
      "createdAt": "2025-10-27T08:52:22.345Z",
      "text": "test!"
    },
    {
      "id": "932f",
      "projectId": 84745,
      "userId": "2",
      "type": "_us",
      "name": "임꺽정",
      "profile": "/images/profile03.jpg",
      "time": "오후 5:52",
      "createdAt": "2025-10-27T08:52:27.665Z",
      "text": "임꺽정이 썼어요"
    },
    {
      "id": "aaac",
      "projectId": 84745,
      "userId": "2",
      "type": "_us",
      "name": "임꺽정",
      "profile": "/images/profile03.jpg",
      "time": "오후 5:53",
      "createdAt": "2025-10-27T08:53:03.756Z",
      "text": "이미지 첨부합니다."
    },
    {
      "id": "08e3",
      "projectId": 84745,
      "userId": "2",
      "type": "_us",
      "name": "임꺽정",
      "profile": "/images/profile03.jpg",
      "time": "오후 5:58",
      "createdAt": "2025-10-27T08:58:18.537Z",
      "text": "250818_수정사항.jpg",
      "file": true
    },
    {
      "id": "2f31",
      "projectId": 84745,
      "userId": "2",
      "type": "_us",
      "name": "임꺽정",
      "profile": "/images/profile03.jpg",
      "time": "오후 5:58",
      "createdAt": "2025-10-27T08:58:18.537Z",
      "text": "이미지 첨부합니다."
    },
    {
      "id": "0985",
      "projectId": 84745,
      "userId": "0",
      "type": "_us",
      "name": "홍길동",
      "profile": "/images/profile01.jpg",
      "time": "오후 6:05",
      "createdAt": "2025-10-28T09:05:44.624Z",
      "text": "입력\n엔터"
    },
    {
      "id": "51b1",
      "projectId": 84745,
      "userId": "0",
      "type": "_us",
      "name": "홍길동",
      "time": "오후 6:09",
      "createdAt": "2025-10-28T09:09:10.936Z",
      "text": "이래도 입력이 되지요?"
    },
    {
      "id": "264d",
      "projectId": 84745,
      "userId": "0",
      "type": "_us",
      "name": "홍길동",
      "time": "오전 11:35",
      "createdAt": "2025-10-30T02:35:08.430Z",
      "text": "(기획서)25년 11월 25FW 주니어 찬스(11.1312.31).pptx",
      "file": true
    },
    {
      "id": "e711",
      "projectId": 84745,
      "userId": "0",
      "type": "_us",
      "name": "홍길동",
      "time": "오전 11:36",
      "createdAt": "2025-10-30T02:36:08.878Z",
      "text": "수정1.pptx",
      "file": true
    },
    {
      "id": "988f",
      "projectId": 84745,
      "userId": "0",
      "type": "_us",
      "name": "홍길동",
      "time": "오전 11:36",
      "createdAt": "2025-10-30T02:36:19.831Z",
      "text": "기획전 수정.pptx",
      "file": true
    },
    {
      "id": "0a8c",
      "projectId": 84745,
      "userId": "0",
      "name": "홍길동",
      "text": "9월 월간네파 수정.pptx",
      "file": true,
      "type": "_us",
      "createdAt": "2025-10-30T02:36:44.005Z",
      "time": "오전 11:36"
    },
    {
      "id": "5307",
      "projectId": 84745,
      "userId": "1",
      "type": "_us",
      "name": "강아지",
      "time": "오전 11:48",
      "createdAt": "2025-10-30T02:48:54.094Z",
      "text": "251023_푸퍼백.zip",
      "file": true
    }
  ]
}